setup.py
chamonix/__init__.py
chamonix/code.py
chamonix/config.py
chamonix/db.py
chamonix/manage.py
chamonix/utils.py
chamonix.egg-info/PKG-INFO
chamonix.egg-info/SOURCES.txt
chamonix.egg-info/dependency_links.txt
chamonix.egg-info/requires.txt
chamonix.egg-info/top_level.txt
chamonix/views/__init__.py
chamonix/views/base.py
chamonix/views/i18n.py