Metadata-Version: 1.1
Name: chamonix
Version: 0.1
Summary: Batteries for webpy application.
Home-page: https://github.com/chaobin/chamonix
Author: Chaobin Tang
Author-email: cbtchn@gmail.com
License: GPLv3
Platform: UNKNOWN
Classifier: Programming Language :: Python :: 2.6
